rgbdslam/__init__.py
rgbdslam/post_process.py
rgbdslam/slam.py
rgbdslam-0.0.4.dist-info/METADATA
rgbdslam-0.0.4.dist-info/WHEEL
rgbdslam-0.0.4.dist-info/entry_points.txt
rgbdslam-0.0.4.dist-info/top_level.txt
rgbdslam-0.0.4.dist-info/RECORD
