Metadata-Version: 2.1
Name: rgbdslam
Version: 0.0.4
Summary: A Python module for RGB-D SLAM using OpenCV, Open3D, and SciPy
Home-page: https://github.com/hugohadfield/rgbdslam
Author: Hugo Hadfield
Author-email: hadfield.hugo@gmail.com
Classifier: Programming Language :: Python :: 3
Classifier: License :: OSI Approved :: MIT License
Classifier: Operating System :: OS Independent
Requires-Python: >=3.6
Requires-Dist: numpy
Requires-Dist: Pillow
Requires-Dist: click
Requires-Dist: matplotlib
Requires-Dist: tqdm
Requires-Dist: pandas
Requires-Dist: open3d
Requires-Dist: opencv-python
Requires-Dist: scipy
Requires-Dist: bayesfilter >=0.0.4
